{
  "Multimedia & Graphics → Video Players": "Video Players",
  "Utilities & Networking → File Compression & Extraction": "File Compression & Extraction",
  "Development → Code Editors & IDEs": "Code Editors & IDEs",
  "Multimedia & Graphics → Image & Design Software": "Image & Design Software",
  "Utilities & Networking → System Optimization": "System Optimization",
  "Multimedia & Graphics → Video Editing & Players": "Video Editing & Players",
  "Multimedia & Graphics → Image & Graphic Design": "Image & Graphic Design",
  "Multimedia & Graphics → Audio & Music Software": "Audio & Music Software",
  "Utilities & Networking → Gaming Tools & Launchers": "Gaming Tools & Launchers",
  "Productivity & Business → Document Editing Suites": "Document Editing Suites",
  "Productivity & Business → Project Management": "Project Management"
}


